versort/__init__.py
versort/__main__.py
versort/base.py
versort/cli.py
versort/sorters/__init__.py
versort/sorters/pep440.py
versort/sorters/semver.py
versort/typing_extra.py
versort-0.1.1.dist-info/entry_points.txt
versort-0.1.1.dist-info/LICENSE
versort-0.1.1.dist-info/WHEEL
versort-0.1.1.dist-info/METADATA
versort-0.1.1.dist-info/RECORD
