Metadata-Version: 2.1
Name: versort
Version: 0.1.1
Summary: Sort versions according to different versioning schemas
Home-page: https://versort.readthedocs.io/
License: BSL-1.0
Author: Jairo Llopis
Author-email: jairo.llopis@tecnativa.com
Requires-Python: >=3.8,<4.0
Classifier: License :: OSI Approved :: Boost Software License 1.0 (BSL-1.0)
Classifier: Programming Language :: Python :: 3
Classifier: Programming Language :: Python :: 3.8
Classifier: Programming Language :: Python :: 3.9
Provides-Extra: docs
Requires-Dist: mkdocs-material (>=6.1.7,<7.0.0); extra == "docs"
Requires-Dist: mkdocstrings (>=0.13.6,<0.14.0); extra == "docs"
Requires-Dist: packaging (>=20.7,<21.0)
Requires-Dist: plumbum (>=1.6.9,<2.0.0)
Requires-Dist: semver (>=2.13.0,<3.0.0)
Project-URL: Repository, https://github.com/Tecnativa/versort
